[
  {
    "goal_id": "FINIS_001",
    "goal": "One of the goals that i have is that i would like to add the ability to look at all of the different audio files that i have and then skim through them somehow and make sure that i get rid of all the ones that i don't actually need",
    "status": "active",
    "derived_from": [
      "2026-03-08_193337.json"
    ]
  },
  {
    "goal_id": "FINIS_002",
    "goal": "I would like to add the goal to go through my repository and look for themes and or functions and or ideas that i'm currently using and then use those as research topics that i can go to google scholar and see if there's documentation about better ways to do things or go out to some of the stack exchanges or other programming forms and see if there's better ways to implement the things that i'm currently doing",
    "status": "active",
    "derived_from": [
      "2026-03-08_195132.json"
    ]
  }
]